BAET/FFmpeg/__init__.py
BAET/FFmpeg/jobs.py
BAET/FFmpeg/probe.py
BAET/__init__.py
BAET/__main__.py
BAET/_config/__init__.py
BAET/_config/console.py
BAET/_config/ffmpeg_version.py
BAET/_config/logging.py
BAET/cli/__init__.py
BAET/cli/cli.py
BAET/cli/command_args.py
BAET/cli/commands/__init__.py
BAET/cli/commands/extract.py
BAET/cli/commands/probe.py
BAET/cli/help_configuration.py
BAET/cli/types.py
BAET/cli/validation/__init__.py
BAET/cli/validation/file_validation.py
BAET/constants.py
BAET/display/__init__.py
BAET/display/job_progress.py
BAET/helpers/__init__.py
BAET/helpers/string_helpers.py
BAET/helpers/time_conversion.py
BAET/theme.py
BAET/typing.py
baet-1.0.1.dist-info/LICENSE
baet-1.0.1.dist-info/METADATA
baet-1.0.1.dist-info/WHEEL
baet-1.0.1.dist-info/entry_points.txt
baet-1.0.1.dist-info/RECORD
