Metadata-Version: 2.1
Name: BAET
Version: 1.0.1
Summary: A tool to bulk extract audio tracks from video using FFmpeg
License: GPL-3.0-or-later
Keywords: ffmpeg,audio,video,extract,bulk,batch
Author: Phillip Smith
Maintainer: TimeTravelPenguin
Maintainer-email: TimeTravelPenguin@gmail.com
Requires-Python: >=3.11,<4.0.0
Classifier: Development Status :: 3 - Alpha
Classifier: Environment :: Console
Classifier: Framework :: Flake8
Classifier: Framework :: Pytest
Classifier: Intended Audience :: End Users/Desktop
Classifier: License :: OSI Approved :: GNU General Public License v3 or later (GPLv3+)
Classifier: Natural Language :: English
Classifier: Operating System :: MacOS
Classifier: Operating System :: Microsoft :: Windows
Classifier: Operating System :: OS Independent
Classifier: Operating System :: POSIX :: Linux
Classifier: Programming Language :: Python :: 3
Classifier: Programming Language :: Python :: 3.11
Classifier: Programming Language :: Python :: 3.12
Classifier: Programming Language :: Python :: Implementation :: CPython
Classifier: Topic :: Multimedia :: Sound/Audio
Classifier: Topic :: Multimedia :: Sound/Audio :: Conversion
Classifier: Topic :: Multimedia :: Video :: Conversion
Classifier: Typing :: Typed
Requires-Dist: asyncio (>=3.4.3,<4.0.0)
Requires-Dist: bidict (>=0.23.1,<0.24.0)
Requires-Dist: click-option-group (>=0.5.6,<0.6.0)
Requires-Dist: ffmpeg-python (>=0.2.0,<0.3.0)
Requires-Dist: more-itertools (>=10.1.0,<11.0.0)
Requires-Dist: rich (>=13.7.0,<14.0.0)
Requires-Dist: rich-argparse (>=1.4.0,<2.0.0)
Requires-Dist: rich-click (>=1.7.3,<2.0.0)
Project-URL: homepage, https://github.com/TimeTravelPenguin/BulkAudioExtractTool
Project-URL: repository, https://github.com/TimeTravelPenguin/BulkAudioExtractTool
